LICENSE.txt
README.md
setup.cfg
setup.py
slicetca/__init__.py
slicetca.egg-info/PKG-INFO
slicetca.egg-info/SOURCES.txt
slicetca.egg-info/dependency_links.txt
slicetca.egg-info/requires.txt
slicetca.egg-info/top_level.txt
slicetca/core/__init__.py
slicetca/core/decompositions.py
slicetca/core/helper_functions.py
slicetca/invariance/__init__.py
slicetca/invariance/analytic_invariance.py
slicetca/invariance/criteria.py
slicetca/invariance/helper.py
slicetca/invariance/invariance.py
slicetca/invariance/iterative_invariance.py
slicetca/invariance/transformations.py
slicetca/plotting/__init__.py
slicetca/plotting/additional.py
slicetca/plotting/factors.py
slicetca/plotting/grid.py
slicetca/run/__init__.py
slicetca/run/decompose.py
slicetca/run/grid_search.py
slicetca/run/utils.py
slicetca/tests/__init__.py
slicetca/tests/tests.py